{   
    "url":{
            "loginUrl" : "web/login/",
            "inboxUrl" : "/web#action=106&active_id=mailbox_inbox&cids=&menu_id=83"
          },
    "credentials" :{ 
                    "password" : "hjul",
                    "email":"uahfauf@gmail.com",
                    "invalidEmail" : "xyx@g.com",
                    "invalidPassword" : "12345678910214",
                    "name" : "Human Singh Hitang"
                   },
    "message" :{
        "validation" : "Please fill out this field.",
        "error" : "Wrong login/password"
    }
   
}
